README.md
cfl/__init__.py
cfl/client.py
cfl/constants.py
cfl/exceptions.py
cfl/leaderboard.py
cfl/logger.py
cfl/types.py
cfl_sdk-0.0.1.dist-info/LICENSE
cfl_sdk-0.0.1.dist-info/METADATA
cfl_sdk-0.0.1.dist-info/WHEEL
cfl_sdk-0.0.1.dist-info/RECORD
