Metadata-Version: 2.3
Name: cfl-sdk
Version: 0.0.1
Summary: Python SDK for the Canadian Football League (CFL) API
License: MIT License
Author: OJ Adeyemi
Author-email: ojieadeyemi@gmail.com
Requires-Python: >=3.10
Classifier: Development Status :: 4 - Beta
Classifier: License :: OSI Approved :: MIT License
Classifier: Operating System :: OS Independent
Classifier: Intended Audience :: Developers
Classifier: Programming Language :: Python :: 3
Classifier: Programming Language :: Python :: 3 :: Only
Classifier: Programming Language :: Python :: 3.10
Classifier: Programming Language :: Python :: 3.11
Classifier: Programming Language :: Python :: 3.12
Classifier: Programming Language :: Python :: 3.13
Classifier: Programming Language :: Python :: Implementation :: CPython
Requires-Dist: beautifulsoup4 (>=4.13.3,<5.0.0)
Requires-Dist: httpx[http2] (>=0.28,<0.30)
